mme/__init__.py
mme/config/__init__.py
mme/config/config.py
mme/config/lazy.py
mme/config/utils.py
mmengine_config-0.10.10.dist-info/licenses/LICENSE
mmengine_config-0.10.10.dist-info/WHEEL
mmengine_config-0.10.10.dist-info/METADATA
mmengine_config-0.10.10.dist-info/RECORD
