Metadata-Version: 2.4
Name: mmengine-config
Version: 0.10.10
Summary: Only config component from mmengine.
Author-email: MMEngine Authors <openmmlab@gmail.com>, Wenyi Tang <wenyitang@outlook.com>
Requires-Python: >=3.11
Classifier: License :: OSI Approved :: Apache Software License
Classifier: Operating System :: OS Independent
Classifier: Programming Language :: Python :: 3.11
Classifier: Programming Language :: Python :: 3.12
Classifier: Programming Language :: Python :: 3.13
Classifier: Topic :: Utilities
License-File: LICENSE
Requires-Dist: addict
Requires-Dist: black
Requires-Dist: rich
Requires-Dist: pytest ; extra == "test"
Requires-Dist: pytest-cov ; extra == "test"
Requires-Dist: mmengine ; extra == "test"
Project-URL: Doc, https://mmengine.readthedocs.io/en/latest/
Project-URL: Home, https://github.com/llteco/mmengine
Provides-Extra: test
